[
	{
		"id": -1000001000,
		"key": "smcfgs000",
		"en|ch|tc|kr": "モンスター:"
	},
	{
		"id": -1000001001,
		"key": "smcfgs001",
		"en|ch|tc|kr": "攻撃力"
	},
	{
		"id": -1000001002,
		"key": "smcfgs002",
		"en|ch|tc|kr": "守備"
	},
	{
		"id": -1000001003,
		"key": "smcfgs003",
		"en|ch|tc|kr": "最大 HP"
	},
	{
		"id": -1000001004,
		"key": "smcfgs004",
		"en|ch|tc|kr": "基礎"
	},
	{
		"id": -1000001005,
		"key": "smcfgs005",
		"en|ch|tc|kr": "(付属剣、刃、槍、拳、指、掌、火、水、雷、木、風、土)"
	},
	{
		"id": -1000001006,
		"key": "smcfgs006",
		"en|ch|tc|kr": "特別モンスター率"
	},
	{
		"id": -1000001007,
		"key": "smcfgs007",
		"en|ch|tc|kr": "経済的:"
	},
	{
		"id": -1000001008,
		"key": "smcfgs008",
		"en|ch|tc|kr": "税率"
	},
	{
		"id": -1000001009,
		"key": "smcfgs009",
		"en|ch|tc|kr": "インフレ率"
	},
	{
		"id": -1000001010,
		"key": "smcfgs010",
		"en|ch|tc|kr": "建築費"
	},
	{
		"id": -1000001011,
		"key": "smcfgs011",
		"en|ch|tc|kr": "銀行口座コスト"
	},
	{
		"id": -1000001012,
		"key": "smcfgs012",
		"en|ch|tc|kr": "銀行手数料"
	},
	{
		"id": -1000001013,
		"key": "smcfgs013",
		"en|ch|tc|kr": "コストを絞り込む"
	},
	{
		"id": -1000001014,
		"key": "smcfgs014",
		"en|ch|tc|kr": "宗派交換手数料"
	},
	{
		"id": -1000001015,
		"key": "smcfgs015",
		"en|ch|tc|kr": "アイテムの値"
	},
	{
		"id": -1000001016,
		"key": "smcfgs016",
		"en|ch|tc|kr": "NPC:"
	},
	{
		"id": -1000001017,
		"key": "smcfgs017",
		"en|ch|tc|kr": "成長率"
	},
	{
		"id": -1000001018,
		"key": "smcfgs018",
		"en|ch|tc|kr": "その他:"
	},
	{
		"id": -1000001019,
		"key": "smcfgs019",
		"en|ch|tc|kr": "レベルアップ経験値"
	},
	{
		"id": -1000001020,
		"key": "smcfgs020",
		"en|ch|tc|kr": "システム:"
	},
	{
		"id": -1000001021,
		"key": "smcfgs021",
		"en|ch|tc|kr": "保存ボタンを非表示にする"
	},
	{
		"id": -1000001022,
		"key": "smcfgs022",
		"en|ch|tc|kr": "リロードボタンを非表示にする"
	},
	{
		"id": -1000001023,
		"key": "smcfgs023",
		"en|ch|tc|kr": "一つの人生"
	},
	{
		"id": -1000001024,
		"key": "smcfgs024",
		"en|ch|tc|kr": "バトルマップを隠す"
	},
	{
		"id": -1000001025,
		"key": "smcfgs025",
		"en|ch|tc|kr": "優先運命レベル"
	},
	{
		"id": -1000001026,
		"key": "smcfgs026",
		"en|ch|tc|kr": "デフォルト"
	},
	{
		"id": -1000001027,
		"key": "smcfgs027",
		"en|ch|tc|kr": "ホワイト"
	},
	{
		"id": -1000001028,
		"key": "smcfgs028",
		"en|ch|tc|kr": "緑"
	},
	{
		"id": -1000001029,
		"key": "smcfgs029",
		"en|ch|tc|kr": "ブルー"
	},
	{
		"id": -1000001030,
		"key": "smcfgs030",
		"en|ch|tc|kr": "バイオレット"
	},
	{
		"id": -1000001031,
		"key": "smcfgs031",
		"en|ch|tc|kr": "黄色"
	},
	{
		"id": -1000001032,
		"key": "smcfgs032",
		"en|ch|tc|kr": "赤"
	},
	{
		"id": -1000001033,
		"key": "smcfgs033",
		"en|ch|tc|kr": "市と宗派の唯一のポータル"
	},
	{
		"id": -1000001034,
		"key": "smcfgs034",
		"en|ch|tc|kr": "宗派交換なし"
	},
	{
		"id": -1000001035,
		"key": "smcfgs035",
		"en|ch|tc|kr": "復活なし"
	},
	{
		"id": -1000001036,
		"key": "smcfgs036",
		"en|ch|tc|kr": "自然にアップグレードを許可する"
	},
	{
		"id": -1000001037,
		"key": "smcfgs037",
		"en|ch|tc|kr": "(この方法では属性/プロパティは成長しません)"
	},
	{
		"id": -1000001038,
		"key": "smcfgs038",
		"en|ch|tc|kr": "ボスは盾を持っています"
	},
	{
		"id": -1000001039,
		"key": "smcfgs039",
		"en|ch|tc|kr": "戦いからは成長なし"
	},
	{
		"id": -1000001040,
		"key": "smcfgs040",
		"en|ch|tc|kr": "戦闘による経験値なし"
	},
	{
		"id": -1000001041,
		"key": "smcfgs041",
		"en|ch|tc|kr": "トレーナーを有効にする"
	},
	{
		"id": -1000001042,
		"key": "smcfgs042",
		"en|ch|tc|kr": "(このオプションの使用はお勧めしません。ゲーム内のホットキー: 【Ctrl+1】)"
	},
	{
		"id": -1000001043,
		"key": "smcfgs043",
		"en|ch|tc|kr": "合計スコア: {0}P"
	},
	{
		"id": -1000001044,
		"key": "smcfgs044",
		"en|ch|tc|kr": "デフォルト"
	},
	{
		"id": -1000001045,
		"key": "smcfgs045",
		"en|ch|tc|kr": "レベル"
	},
	{
		"id": -1000001046,
		"key": "smcfgs046",
		"en|ch|tc|kr": "これらの設定を適用するには、新しいゲームを開始する必要があります。"
	},
	{
		"id": -1000001047,
		"key": "smcfgs047",
		"en|ch|tc|kr": "NPC 金額"
	},
	{
		"id": -1000001048,
		"key": "smcfgs048",
		"en|ch|tc|kr": "（必須 RAM: {0}MB）"
	},
	{
		"id": -1000001049,
		"key": "smcfgs049",
		"en|ch|tc|kr": "(シールド、爆発、増殖付属)"
	},
	{
		"id": -1000001050,
		"key": "smcfgs050",
		"en|ch|tc|kr": "時間の経過とともに街の発展を許可する"
	},
	{
		"id": -1000001051,
		"key": "smcfgs051",
		"en|ch|tc|kr": "成長速度"
	},
	{
		"id": -1000001052,
		"key": "smcfgs052",
		"en|ch|tc|kr": "(プレイヤー、NPC、モンスターを含む)"
	},
	{
		"id": -1000001053,
		"key": "smcfgs053",
		"en|ch|tc|kr": "{1} か月ごと ({0}P)"
	},
	{
		"id": -1000001054,
		"key": "smcfgs054",
		"en|ch|tc|kr": "構成のエクスポート"
	},
	{
		"id": -1000001055,
		"key": "smcfgs055",
		"en|ch|tc|kr": "構成のインポート"
	},
	{
		"id": -1000001056,
		"key": "smcfgs056",
		"en|ch|tc|kr": "死亡時のロストアイテム"
	},
	{
		"id": -1000001057,
		"key": "smcfgs057",
		"en|ch|tc|kr": "(最初の町を含む)"
	},
	{
		"id": -1000001058,
		"key": "smcfgs058",
		"en|ch|tc|kr": "モンスターはプレイヤーに依存します"
	},
	{
		"id": -1000001059,
		"key": "smcfgs059",
		"en|ch|tc|kr": "紛失後の自動保存"
	},
	{
		"id": -1000001060,
		"key": "smcfgs060",
		"en|ch|tc|kr": "(ヒーリング期間は来月にスキップされます)"
	},
	{
		"id": -1000001101,
		"key": "smcfgs101",
		"en|ch|tc|kr": "{1}% ({0}P)"
	},
	{
		"id": -1000001102,
		"key": "smcfgs102",
		"en|ch|tc|kr": "({0} P)"
	},
	{
		"id": -1000001103,
		"key": "smcfgs103",
		"en|ch|tc|kr": "{1} ({0}P)"
	},
	{
		"id": -1000001104,
		"key": "smcfgs104",
		"en|ch|tc|kr": "スタートアップ"
	},
	{
		"id": -1000001105,
		"key": "smcfgs105",
		"en|ch|tc|kr": "パワーアップ：あらゆる面に特化したキャラクター。\nスピードアップ：スピードに特化したキャラクター。\n道士：魔法に特化したキャラクター。\nPro Atk：攻撃に特化したキャラクター。\nPro Def：防御に特化したキャラクター。\n天使：防御と保護に重点を置いた心優しい天使。\n悪：攻撃に特化した、誰からも敬遠される悪魔。\n商人：富で他人を押しつぶす商人。"
	},
	{
		"id": -1000001106,
		"key": "smcfgs106",
		"en|ch|tc|kr": "プレイヤーの役割"
	},
	{
		"id": -1000001107,
		"key": "smcfgs107",
		"en|ch|tc|kr": "ランダム"
	},
	{
		"id": -1000001108,
		"key": "smcfgs108",
		"en|ch|tc|kr": "パワーアップ"
	},
	{
		"id": -1000001109,
		"key": "smcfgs109",
		"en|ch|tc|kr": "スピードアップ"
	},
	{
		"id": -1000001110,
		"key": "smcfgs110",
		"en|ch|tc|kr": "道教者"
	},
	{
		"id": -1000001111,
		"key": "smcfgs111",
		"en|ch|tc|kr": "プロアタック"
	},
	{
		"id": -1000001112,
		"key": "smcfgs112",
		"en|ch|tc|kr": "プロデフ"
	},
	{
		"id": -1000001113,
		"key": "smcfgs113",
		"en|ch|tc|kr": "エンジェル"
	},
	{
		"id": -1000001114,
		"key": "smcfgs114",
		"en|ch|tc|kr": "悪"
	},
	{
		"id": -1000001115,
		"key": "smcfgs115",
		"en|ch|tc|kr": "商人"
	},
	{
		"id": -1000001116,
		"key": "smcfgs116",
		"en|ch|tc|kr": "マーケットアイテム"
	},
	{
		"id": -1000001117,
		"key": "smcfgs117",
		"en|ch|tc|kr": "NPC 参加率"
	},
	{
		"id": -1000001118,
		"key": "smcfgs118",
		"en|ch|tc|kr": "攻撃率を取得する"
	},
	{
		"id": -1000001119,
		"key": "smcfgs119",
		"en|ch|tc|kr": "(警告: この機能は RAM を大量に消費するため、遅延が発生する可能性があります)"
	},
	{
		"id": -1000001120,
		"key": "smcfgs120",
		"en|ch|tc|kr": "セーブデータ"
	},
	{
		"id": -1000001121,
		"key": "smcfgs121",
		"en|ch|tc|kr": "Mod 構成"
	},
	{
		"id": -1000001122,
		"key": "smcfgs122",
		"en|ch|tc|kr": "課税なし"
	},
	{
		"id": -1000001123,
		"key": "smcfgs123",
		"en|ch|tc|kr": "市場アイテムなし"
	},
	{
		"id": -1000001124,
		"key": "smcfgs124",
		"en|ch|tc|kr": "ストーカー禁止"
	},
	{
		"id": -1000001125,
		"key": "smcfgs125",
		"en|ch|tc|kr": "いいえ Qi 栽培"
	},
	{
		"id": -1000001126,
		"key": "smcfgs126",
		"en|ch|tc|kr": "（NPCは依然として税金を支払わなければなりません）"
	},
	{
		"id": -1000001127,
		"key": "smcfgs127",
		"en|ch|tc|kr": "ハードコア:"
	},
	{
		"id": -1000001128,
		"key": "smcfgs128",
		"en|ch|tc|kr": "(この設定は毎月の処理時間に影響します)"
	},
	{
		"id": -1000001129,
		"key": "smcfgs129",
		"en|ch|tc|kr": "死亡/喪失時に失われる寿命"
	},
	{
		"id": -1000001130,
		"key": "smcfgs130",
		"en|ch|tc|kr": "各町のマックスセラーズ"
	},
	{
		"id": -1000001131,
		"key": "smcfgs131",
		"en|ch|tc|kr": "販売アイテムの最大購入者数"
	},
	{
		"id": -1000001132,
		"key": "smcfgs132",
		"en|ch|tc|kr": "{0}"
	},
	{
		"id": -1000001133,
		"key": "smcfgs133",
		"en|ch|tc|kr": "販売者の最大アイテム数"
	},
	{
		"id": -1000001134,
		"key": "smcfgs134",
		"en|ch|tc|kr": "進行方向/近くの領域でのみアクティブ"
	},
	{
		"id": -1000001135,
		"key": "smcfgs135",
		"en|ch|tc|kr": "(処理時間を短縮しますが、NPCに影響します)"
	},
	{
		"id": -1000001136,
		"key": "smcfgs136",
		"en|ch|tc|kr": "街の戦争後に建物を破壊する"
	},
	{
		"id": -1000001137,
		"key": "smcfgs137",
		"en|ch|tc|kr": "神武器の修理を許可する"
	},
	{
		"id": -1000001138,
		"key": "smcfgs138",
		"en|ch|tc|kr": "すべての機能は最も近いユニットに適用されます"
	},
	{
		"id": -1000001139,
		"key": "smcfgs139",
		"en|ch|tc|kr": "死亡時に失うお金"
	}
]