[
  {
    "id": "1",
    "rewardID": "1011",
    "condition": "0",
    "itemType": "1",
    "item": "10001",
    "numMin": "1",
    "numMax": "1",
    "group": "1",
    "firstRewardGroup": "0",
    "layMax": "1",
    "noLuckAffect": "0",
    "weight": "20000"
  },
  {
    "id": "2",
    "rewardID": "1021",
    "condition": "0",
    "itemType": "1",
    "item": "1011051",
    "numMin": "1",
    "numMax": "1",
    "group": "1",
    "firstRewardGroup": "0",
    "layMax": "1",
    "noLuckAffect": "0",
    "weight": "200"
  },
  {
    "id": "3",
    "rewardID": "1031",
    "condition": "0",
    "itemType": "1",
    "item": "10001",
    "numMin": "2",
    "numMax": "4",
    "group": "1",
    "firstRewardGroup": "0",
    "layMax": "1",
    "noLuckAffect": "0",
    "weight": "20000"
  },
  {
    "id": "4",
    "rewardID": "1041",
    "condition": "0",
    "itemType": "1",
    "item": "10001",
    "numMin": "2",
    "numMax": "4",
    "group": "1",
    "firstRewardGroup": "0",
    "layMax": "1",
    "noLuckAffect": "0",
    "weight": "20000"
  },
  {
    "id": "5",
    "rewardID": "1051",
    "condition": "0",
    "itemType": "1",
    "item": "10001",
    "numMin": "15",
    "numMax": "30",
    "group": "1",
    "firstRewardGroup": "0",
    "layMax": "1",
    "noLuckAffect": "0",
    "weight": "20000"
  },
  {
    "id": "6",
    "rewardID": "1061",
    "condition": "0",
    "itemType": "1",
    "item": "10001",
    "numMin": "30",
    "numMax": "40",
    "group": "1",
    "firstRewardGroup": "0",
    "layMax": "1",
    "noLuckAffect": "0",
    "weight": "20000"
  },
  {
    "id": "7",
    "rewardID": "1071",
    "condition": "0",
    "itemType": "1",
    "item": "10001",
    "numMin": "200",
    "numMax": "260",
    "group": "1",
    "firstRewardGroup": "0",
    "layMax": "1",
    "noLuckAffect": "0",
    "weight": "20000"
  },
  {
    "id": "8",
    "rewardID": "1081",
    "condition": "0",
    "itemType": "1",
    "item": "10001",
    "numMin": "2",
    "numMax": "4",
    "group": "1",
    "firstRewardGroup": "0",
    "layMax": "1",
    "noLuckAffect": "0",
    "weight": "20000"
  },
  {
    "id": "9",
    "rewardID": "1091",
    "condition": "0",
    "itemType": "1",
    "item": "10001",
    "numMin": "2",
    "numMax": "4",
    "group": "1",
    "firstRewardGroup": "0",
    "layMax": "1",
    "noLuckAffect": "0",
    "weight": "20000"
  },
  {
    "id": "10",
    "rewardID": "1101",
    "condition": "0",
    "itemType": "1",
    "item": "10001",
    "numMin": "2",
    "numMax": "4",
    "group": "1",
    "firstRewardGroup": "0",
    "layMax": "1",
    "noLuckAffect": "0",
    "weight": "20000"
  },
  {
    "id": "11",
    "rewardID": "1111",
    "condition": "0",
    "itemType": "1",
    "item": "10001",
    "numMin": "2",
    "numMax": "4",
    "group": "1",
    "firstRewardGroup": "0",
    "layMax": "1",
    "noLuckAffect": "0",
    "weight": "20000"
  },
  {
    "id": "12",
    "rewardID": "1121",
    "condition": "0",
    "itemType": "1",
    "item": "10001",
    "numMin": "2",
    "numMax": "4",
    "group": "1",
    "firstRewardGroup": "0",
    "layMax": "1",
    "noLuckAffect": "0",
    "weight": "20000"
  },
  {
    "id": "13",
    "rewardID": "1131",
    "condition": "0",
    "itemType": "1",
    "item": "10001",
    "numMin": "2",
    "numMax": "4",
    "group": "1",
    "firstRewardGroup": "0",
    "layMax": "1",
    "noLuckAffect": "0",
    "weight": "20000"
  },
  {
    "id": "14",
    "rewardID": "1141",
    "condition": "0",
    "itemType": "1",
    "item": "10001",
    "numMin": "2",
    "numMax": "4",
    "group": "1",
    "firstRewardGroup": "0",
    "layMax": "1",
    "noLuckAffect": "0",
    "weight": "20000"
  },
  {
    "id": "15",
    "rewardID": "1151",
    "condition": "0",
    "itemType": "1",
    "item": "10001",
    "numMin": "2",
    "numMax": "4",
    "group": "1",
    "firstRewardGroup": "0",
    "layMax": "1",
    "noLuckAffect": "0",
    "weight": "20000"
  },
  {
    "id": "16",
    "rewardID": "1161",
    "condition": "0",
    "itemType": "1",
    "item": "10001",
    "numMin": "2",
    "numMax": "4",
    "group": "1",
    "firstRewardGroup": "0",
    "layMax": "1",
    "noLuckAffect": "0",
    "weight": "20000"
  },
  {
    "id": "17",
    "rewardID": "1171",
    "condition": "0",
    "itemType": "1",
    "item": "10001",
    "numMin": "2",
    "numMax": "4",
    "group": "1",
    "firstRewardGroup": "0",
    "layMax": "1",
    "noLuckAffect": "0",
    "weight": "20000"
  },
  {
    "id": "18",
    "rewardID": "1181",
    "condition": "0",
    "itemType": "1",
    "item": "10001",
    "numMin": "2",
    "numMax": "4",
    "group": "1",
    "firstRewardGroup": "0",
    "layMax": "1",
    "noLuckAffect": "0",
    "weight": "20000"
  },
  {
    "id": "19",
    "rewardID": "1191",
    "condition": "0",
    "itemType": "1",
    "item": "10001",
    "numMin": "2",
    "numMax": "4",
    "group": "1",
    "firstRewardGroup": "0",
    "layMax": "1",
    "noLuckAffect": "0",
    "weight": "20000"
  },
  {
    "id": "20",
    "rewardID": "1201",
    "condition": "0",
    "itemType": "1",
    "item": "10001",
    "numMin": "2",
    "numMax": "4",
    "group": "1",
    "firstRewardGroup": "0",
    "layMax": "1",
    "noLuckAffect": "0",
    "weight": "20000"
  },
  {
    "id": "21",
    "rewardID": "2011",
    "condition": "0",
    "itemType": "9",
    "item": "104",
    "numMin": "1",
    "numMax": "1",
    "group": "1",
    "firstRewardGroup": "0",
    "layMax": "1",
    "noLuckAffect": "0",
    "weight": "10"
  },
  {
    "id": "22",
    "rewardID": "2021",
    "condition": "0",
    "itemType": "9",
    "item": "104",
    "numMin": "1",
    "numMax": "1",
    "group": "1",
    "firstRewardGroup": "0",
    "layMax": "1",
    "noLuckAffect": "0",
    "weight": "2000"
  },
  {
    "id": "23",
    "rewardID": "2021",
    "condition": "0",
    "itemType": "9",
    "item": "105",
    "numMin": "1",
    "numMax": "1",
    "group": "1",
    "firstRewardGroup": "0",
    "layMax": "1",
    "noLuckAffect": "0",
    "weight": "1000"
  },
  {
    "id": "24",
    "rewardID": "2031",
    "condition": "0",
    "itemType": "9",
    "item": "106",
    "numMin": "1",
    "numMax": "1",
    "group": "1",
    "firstRewardGroup": "0",
    "layMax": "1",
    "noLuckAffect": "0",
    "weight": "20000"
  },
  {
    "id": "25",
    "rewardID": "2031",
    "condition": "0",
    "itemType": "9",
    "item": "104",
    "numMin": "1",
    "numMax": "1",
    "group": "2",
    "firstRewardGroup": "0",
    "layMax": "1",
    "noLuckAffect": "0",
    "weight": "5000"
  },
  {
    "id": "26",
    "rewardID": "2031",
    "condition": "0",
    "itemType": "9",
    "item": "105",
    "numMin": "1",
    "numMax": "1",
    "group": "2",
    "firstRewardGroup": "0",
    "layMax": "1",
    "noLuckAffect": "0",
    "weight": "5000"
  },
  {
    "id": "27",
    "rewardID": "2031",
    "condition": "0",
    "itemType": "9",
    "item": "104",
    "numMin": "1",
    "numMax": "1",
    "group": "3",
    "firstRewardGroup": "0",
    "layMax": "1",
    "noLuckAffect": "0",
    "weight": "5000"
  },
  {
    "id": "28",
    "rewardID": "2031",
    "condition": "0",
    "itemType": "9",
    "item": "105",
    "numMin": "1",
    "numMax": "1",
    "group": "3",
    "firstRewardGroup": "0",
    "layMax": "1",
    "noLuckAffect": "0",
    "weight": "5000"
  },
  {
    "id": "29",
    "rewardID": "2041",
    "condition": "0",
    "itemType": "9",
    "item": "104",
    "numMin": "1",
    "numMax": "1",
    "group": "4",
    "firstRewardGroup": "0",
    "layMax": "1",
    "noLuckAffect": "0",
    "weight": "5000"
  },
  {
    "id": "30",
    "rewardID": "2041",
    "condition": "0",
    "itemType": "9",
    "item": "105",
    "numMin": "1",
    "numMax": "1",
    "group": "4",
    "firstRewardGroup": "0",
    "layMax": "1",
    "noLuckAffect": "0",
    "weight": "5000"
  },
  {
    "id": "31",
    "rewardID": "2041",
    "condition": "0",
    "itemType": "9",
    "item": "104",
    "numMin": "1",
    "numMax": "1",
    "group": "5",
    "firstRewardGroup": "0",
    "layMax": "1",
    "noLuckAffect": "0",
    "weight": "5000"
  },
  {
    "id": "32",
    "rewardID": "2041",
    "condition": "0",
    "itemType": "9",
    "item": "105",
    "numMin": "1",
    "numMax": "1",
    "group": "5",
    "firstRewardGroup": "0",
    "layMax": "1",
    "noLuckAffect": "0",
    "weight": "5000"
  },
  {
    "id": "33",
    "rewardID": "2051",
    "condition": "0",
    "itemType": "1",
    "item": "1011051",
    "numMin": "1",
    "numMax": "1",
    "group": "2",
    "firstRewardGroup": "0",
    "layMax": "1",
    "noLuckAffect": "0",
    "weight": "1000"
  },
  {
    "id": "34",
    "rewardID": "2061",
    "condition": "0",
    "itemType": "1",
    "item": "1011051",
    "numMin": "1",
    "numMax": "1",
    "group": "2",
    "firstRewardGroup": "0",
    "layMax": "1",
    "noLuckAffect": "0",
    "weight": "1000"
  },
  {
    "id": "35",
    "rewardID": "2071",
    "condition": "0",
    "itemType": "1",
    "item": "1011051",
    "numMin": "1",
    "numMax": "1",
    "group": "2",
    "firstRewardGroup": "0",
    "layMax": "1",
    "noLuckAffect": "0",
    "weight": "1000"
  },
  {
    "id": "36",
    "rewardID": "2081",
    "condition": "0",
    "itemType": "1",
    "item": "1011051",
    "numMin": "1",
    "numMax": "1",
    "group": "2",
    "firstRewardGroup": "0",
    "layMax": "1",
    "noLuckAffect": "0",
    "weight": "1000"
  },
  {
    "id": "37",
    "rewardID": "2091",
    "condition": "0",
    "itemType": "1",
    "item": "1011051",
    "numMin": "1",
    "numMax": "1",
    "group": "2",
    "firstRewardGroup": "0",
    "layMax": "1",
    "noLuckAffect": "0",
    "weight": "1000"
  },
  {
    "id": "38",
    "rewardID": "2101",
    "condition": "0",
    "itemType": "1",
    "item": "1011051",
    "numMin": "1",
    "numMax": "1",
    "group": "2",
    "firstRewardGroup": "0",
    "layMax": "1",
    "noLuckAffect": "0",
    "weight": "1000"
  },
  {
    "id": "39",
    "rewardID": "2111",
    "condition": "0",
    "itemType": "1",
    "item": "1011051",
    "numMin": "1",
    "numMax": "1",
    "group": "2",
    "firstRewardGroup": "0",
    "layMax": "1",
    "noLuckAffect": "0",
    "weight": "1000"
  },
  {
    "id": "40",
    "rewardID": "2121",
    "condition": "0",
    "itemType": "1",
    "item": "1011051",
    "numMin": "1",
    "numMax": "1",
    "group": "2",
    "firstRewardGroup": "0",
    "layMax": "1",
    "noLuckAffect": "0",
    "weight": "1000"
  },
  {
    "id": "41",
    "rewardID": "2131",
    "condition": "0",
    "itemType": "1",
    "item": "1011051",
    "numMin": "1",
    "numMax": "1",
    "group": "2",
    "firstRewardGroup": "0",
    "layMax": "1",
    "noLuckAffect": "0",
    "weight": "1000"
  },
  {
    "id": "42",
    "rewardID": "2141",
    "condition": "0",
    "itemType": "1",
    "item": "1011051",
    "numMin": "1",
    "numMax": "1",
    "group": "2",
    "firstRewardGroup": "0",
    "layMax": "1",
    "noLuckAffect": "0",
    "weight": "1000"
  },
  {
    "id": "43",
    "rewardID": "2151",
    "condition": "0",
    "itemType": "1",
    "item": "1011051",
    "numMin": "1",
    "numMax": "1",
    "group": "2",
    "firstRewardGroup": "0",
    "layMax": "1",
    "noLuckAffect": "0",
    "weight": "1000"
  },
  {
    "id": "44",
    "rewardID": "2161",
    "condition": "0",
    "itemType": "1",
    "item": "1011051",
    "numMin": "1",
    "numMax": "1",
    "group": "2",
    "firstRewardGroup": "0",
    "layMax": "1",
    "noLuckAffect": "0",
    "weight": "1000"
  },
  {
    "id": "45",
    "rewardID": "2171",
    "condition": "0",
    "itemType": "1",
    "item": "1011051",
    "numMin": "1",
    "numMax": "1",
    "group": "2",
    "firstRewardGroup": "0",
    "layMax": "1",
    "noLuckAffect": "0",
    "weight": "1000"
  },
  {
    "id": "46",
    "rewardID": "2181",
    "condition": "0",
    "itemType": "1",
    "item": "1011051",
    "numMin": "1",
    "numMax": "1",
    "group": "2",
    "firstRewardGroup": "0",
    "layMax": "1",
    "noLuckAffect": "0",
    "weight": "1000"
  },
  {
    "id": "47",
    "rewardID": "2191",
    "condition": "0",
    "itemType": "1",
    "item": "1011051",
    "numMin": "1",
    "numMax": "1",
    "group": "2",
    "firstRewardGroup": "0",
    "layMax": "1",
    "noLuckAffect": "0",
    "weight": "1000"
  },
  {
    "id": "48",
    "rewardID": "2201",
    "condition": "0",
    "itemType": "1",
    "item": "1011051",
    "numMin": "1",
    "numMax": "1",
    "group": "2",
    "firstRewardGroup": "0",
    "layMax": "1",
    "noLuckAffect": "0",
    "weight": "1000"
  },
  {
    "id": "49",
    "rewardID": "10002",
    "condition": "0",
    "itemType": "1",
    "item": "10002",
    "numMin": "1",
    "numMax": "1",
    "group": "-1",
    "firstRewardGroup": "0",
    "layMax": "1",
    "noLuckAffect": "0",
    "weight": "20000"
  },
  {
    "id": "50",
    "rewardID": "20001",
    "condition": "0",
    "itemType": "9",
    "item": "104",
    "numMin": "1",
    "numMax": "1",
    "group": "1",
    "firstRewardGroup": "0",
    "layMax": "1",
    "noLuckAffect": "0",
    "weight": "200"
  },
  {
    "id": "51",
    "rewardID": "20001",
    "condition": "0",
    "itemType": "1",
    "item": "1011051",
    "numMin": "1",
    "numMax": "1",
    "group": "1",
    "firstRewardGroup": "0",
    "layMax": "1",
    "noLuckAffect": "0",
    "weight": "20000"
  },
  {
    "id": "52",
    "rewardID": "30001",
    "condition": "0",
    "itemType": "1",
    "item": "1011051",
    "numMin": "1",
    "numMax": "1",
    "group": "1",
    "firstRewardGroup": "0",
    "layMax": "1",
    "noLuckAffect": "0",
    "weight": "20000"
  }
]